vulnerability_analyzer/__init__.py
vulnerability_analyzer/_version.py
vulnerability_analyzer/cli.py
vulnerability_analyzer/analysis/__init__.py
vulnerability_analyzer/analysis/nmap.py
vulnerability_analyzer/analysis/pcap.py
vulnerability_analyzer/vulnerability/__init__.py
vulnerability_analyzer/vulnerability/matcher.py
vulnerability_analyzer-2.0.0.dist-info/licenses/LICENSE
vulnerability_analyzer-2.0.0.dist-info/METADATA
vulnerability_analyzer-2.0.0.dist-info/WHEEL
vulnerability_analyzer-2.0.0.dist-info/entry_points.txt
vulnerability_analyzer-2.0.0.dist-info/top_level.txt
vulnerability_analyzer-2.0.0.dist-info/RECORD
