Metadata-Version: 2.4
Name: vulnerability-analyzer
Version: 2.0.0
Summary: Streamlined network security analysis for PCAP files and Nmap scans with flexible output formats
Author-email: D14b0l1c <security@example.com>
Maintainer-email: D14b0l1c <security@example.com>
License-Expression: MIT
Project-URL: Homepage, https://github.com/D14b0l1c/vulnerability-analyzer
Project-URL: Repository, https://github.com/D14b0l1c/vulnerability-analyzer.git
Project-URL: Issues, https://github.com/D14b0l1c/vulnerability-analyzer/issues
Project-URL: Documentation, https://github.com/D14b0l1c/vulnerability-analyzer#readme
Keywords: vulnerability,security,network,pcap,nmap,analysis,penetration-testing,cybersecurity
Classifier: Development Status :: 5 - Production/Stable
Classifier: Intended Audience :: Information Technology
Classifier: Intended Audience :: System Administrators
Classifier: Intended Audience :: Developers
Classifier: Operating System :: OS Independent
Classifier: Programming Language :: Python :: 3
Classifier: Programming Language :: Python :: 3.8
Classifier: Programming Language :: Python :: 3.9
Classifier: Programming Language :: Python :: 3.10
Classifier: Programming Language :: Python :: 3.11
Classifier: Programming Language :: Python :: 3.12
Classifier: Topic :: Security
Classifier: Topic :: System :: Networking :: Monitoring
Classifier: Topic :: System :: Systems Administration
Classifier: Environment :: Console
Requires-Python: >=3.8
License-File: LICENSE
Requires-Dist: pandas>=1.3.0
Provides-Extra: dev
Requires-Dist: pytest>=6.0; extra == "dev"
Requires-Dist: pytest-cov; extra == "dev"
Requires-Dist: black; extra == "dev"
Requires-Dist: flake8; extra == "dev"
Requires-Dist: mypy; extra == "dev"
Dynamic: license-file
